y2j/__init__.py
y2j/__main__.py
y2j-0.0.3.dist-info/LICENSE
y2j-0.0.3.dist-info/METADATA
y2j-0.0.3.dist-info/WHEEL
y2j-0.0.3.dist-info/entry_points.txt
y2j-0.0.3.dist-info/top_level.txt
y2j-0.0.3.dist-info/zip-safe
y2j-0.0.3.dist-info/RECORD
