Metadata-Version: 2.1
Name: y2j
Version: 0.0.3
Summary: A CLI tool for converting YAML to JSON.
Home-page: https://github.com/SheepGotoHeaven/y2j
Author: Neal Ormsbee
Author-email: neal.ormsbee@gmail.com
License: MIT
Platform: UNKNOWN
Classifier: Programming Language :: Python :: 3
Classifier: License :: OSI Approved :: MIT License
Classifier: Operating System :: OS Independent
Requires-Dist: pyyaml
